{"map":"twctf2m8","version":1,"items":[{"kind":"rl","x":-168,"y":-652,"z":28},{"kind":"quad","x":-168,"y":145,"z":-8},{"kind":"lg","x":-168,"y":93,"z":200},{"kind":"cells","x":-128,"y":58,"z":200},{"kind":"cells","x":-232,"y":58,"z":200},{"kind":"ssg","x":-2398,"y":-1005,"z":76},{"kind":"ng","x":-2398,"y":-597,"z":76},{"kind":"h25","x":-2110,"y":-613,"z":76},{"kind":"h25","x":-2050,"y":-613,"z":76},{"kind":"h25","x":-2050,"y":-1021,"z":76},{"kind":"h25","x":-2110,"y":-1021,"z":76},{"kind":"shells","x":-2322,"y":-1017,"z":76},{"kind":"nails","x":-2322,"y":-609,"z":76},{"kind":"sng","x":-2037,"y":-976,"z":276},{"kind":"h25","x":-2721,"y":-327,"z":276},{"kind":"h25","x":-2721,"y":-1305,"z":276},{"kind":"nails","x":-2356,"y":-1107,"z":196},{"kind":"nails","x":-2406,"y":-1107,"z":196},{"kind":"shells","x":-2338,"y":-517,"z":196},{"kind":"mh","x":-3021,"y":-606,"z":408},{"kind":"rockets","x":-3188,"y":-598,"z":-112},{"kind":"ya","x":-2927,"y":-822,"z":-352},{"kind":"rockets","x":-1697,"y":-830,"z":-280},{"kind":"h25","x":-2881,"y":-815,"z":-352},{"kind":"gl","x":-2762,"y":-1298,"z":-280},{"kind":"ra","x":-1651,"y":-789,"z":-280},{"kind":"sng","x":-1695,"y":-800,"z":36},{"kind":"h25","x":-1434,"y":-688,"z":-32},{"kind":"h25","x":-1434,"y":-944,"z":-32},{"kind":"nails","x":-1700,"y":-920,"z":-116},{"kind":"shells","x":-1700,"y":-704,"z":-116},{"kind":"cells","x":-2023,"y":-297,"z":276},{"kind":"cells","x":-2023,"y":-335,"z":276},{"kind":"h25","x":-2025,"y":-1293,"z":276},{"kind":"nails","x":-2023,"y":-1334,"z":276},{"kind":"h25","x":-2056,"y":-736,"z":196},{"kind":"h25","x":-2056,"y":-896,"z":196},{"kind":"ya","x":-2030,"y":-609,"z":276},{"kind":"h25","x":-2881,"y":-859,"z":-352},{"kind":"ssg","x":-580,"y":-636,"z":-172},{"kind":"shells","x":-623,"y":-636,"z":-172},{"kind":"ya","x":-168,"y":-368,"z":-172},{"kind":"cells","x":68,"y":-556,"z":-172},{"kind":"cells","x":-407,"y":-556,"z":-172},{"kind":"shells","x":-408,"y":-332,"z":64},{"kind":"h25","x":-400,"y":-1004,"z":40},{"kind":"h25","x":-688,"y":-1004,"z":4},{"kind":"h25","x":352,"y":-1004,"z":4},{"kind":"h25","x":68,"y":-1004,"z":40},{"kind":"h25","x":248,"y":425,"z":200},{"kind":"h25","x":-616,"y":425,"z":200},{"kind":"h25","x":-1138,"y":-234,"z":-32},{"kind":"nails","x":-644,"y":-1008,"z":4},{"kind":"shells","x":70,"y":-332,"z":64},{"kind":"ng","x":-696,"y":-56,"z":0},{"kind":"h25","x":-2978,"y":-1083,"z":-224},{"kind":"h25","x":-2978,"y":-1039,"z":-224},{"kind":"shells","x":-2657,"y":-1145,"z":-136},{"kind":"nails","x":-2765,"y":-834,"z":-352},{"kind":"ssg","x":2038,"y":-1005,"z":76},{"kind":"ng","x":2038,"y":-597,"z":76},{"kind":"h25","x":1734,"y":-613,"z":76},{"kind":"h25","x":1674,"y":-613,"z":76},{"kind":"h25","x":1674,"y":-1021,"z":76},{"kind":"h25","x":1734,"y":-1021,"z":76},{"kind":"shells","x":1964,"y":-1016,"z":76},{"kind":"nails","x":1964,"y":-608,"z":76},{"kind":"sng","x":1677,"y":-976,"z":276},{"kind":"h25","x":2353,"y":-327,"z":276},{"kind":"h25","x":2353,"y":-1305,"z":276},{"kind":"nails","x":1980,"y":-1107,"z":196},{"kind":"nails","x":2030,"y":-1107,"z":196},{"kind":"shells","x":1962,"y":-517,"z":196},{"kind":"mh","x":2653,"y":-606,"z":408},{"kind":"rockets","x":2836,"y":-598,"z":-112},{"kind":"ya","x":2567,"y":-822,"z":-352},{"kind":"rockets","x":1345,"y":-830,"z":-280},{"kind":"h25","x":2509,"y":-815,"z":-352},{"kind":"gl","x":2402,"y":-1298,"z":-280},{"kind":"ra","x":1320,"y":-789,"z":-280},{"kind":"sng","x":1335,"y":-800,"z":36},{"kind":"h25","x":1082,"y":-688,"z":-32},{"kind":"h25","x":1082,"y":-944,"z":-32},{"kind":"nails","x":1340,"y":-920,"z":-116},{"kind":"shells","x":1340,"y":-704,"z":-116},{"kind":"cells","x":1659,"y":-297,"z":276},{"kind":"cells","x":1659,"y":-335,"z":276},{"kind":"h25","x":1661,"y":-1293,"z":276},{"kind":"nails","x":1659,"y":-1334,"z":276},{"kind":"h25","x":1686,"y":-736,"z":196},{"kind":"h25","x":1686,"y":-896,"z":196},{"kind":"ya","x":1670,"y":-609,"z":276},{"kind":"h25","x":2509,"y":-859,"z":-352},{"kind":"ssg","x":244,"y":-624,"z":-172},{"kind":"shells","x":288,"y":-624,"z":-172},{"kind":"h25","x":770,"y":-234,"z":-32},{"kind":"nails","x":298,"y":-1008,"z":4},{"kind":"ng","x":360,"y":-60,"z":0},{"kind":"h25","x":2618,"y":-1083,"z":-224},{"kind":"h25","x":2618,"y":-1039,"z":-224},{"kind":"shells","x":2298,"y":-1145,"z":-136},{"kind":"nails","x":2405,"y":-834,"z":-352},{"kind":"ring","x":-168,"y":288,"z":380},{"kind":"nails","x":-724,"y":-56,"z":3},{"kind":"nails","x":388,"y":-60,"z":16}]}