{
 "map": "gauntlet",
 "version": 1,
 "entities": [
  {
   "type": "item",
   "class": "weapon_grenadelauncher",
   "kind": "gl",
   "name": "gl",
   "x": 0,
   "y": 0,
   "z": 27
  },
  {
   "type": "item",
   "class": "item_spikes",
   "kind": "nails",
   "name": "nails-1",
   "x": -144,
   "y": -974,
   "z": 36
  },
  {
   "type": "item",
   "class": "item_spikes",
   "kind": "nails",
   "name": "nails-2",
   "x": -144,
   "y": 960,
   "z": 44
  },
  {
   "type": "item",
   "class": "item_spikes",
   "kind": "nails",
   "name": "nails-3",
   "x": 128,
   "y": -960,
   "z": 44
  },
  {
   "type": "item",
   "class": "item_spikes",
   "kind": "nails",
   "name": "nails-4",
   "x": 128,
   "y": 960,
   "z": 32
  },
  {
   "type": "item",
   "class": "weapon_nailgun",
   "kind": "ng",
   "name": "ng-1",
   "x": -144,
   "y": -976,
   "z": -60
  },
  {
   "type": "item",
   "class": "weapon_nailgun",
   "kind": "ng",
   "name": "ng-2",
   "x": -144,
   "y": 979,
   "z": -76
  },
  {
   "type": "item",
   "class": "weapon_nailgun",
   "kind": "ng",
   "name": "ng-3",
   "x": 148,
   "y": 979,
   "z": -64
  },
  {
   "type": "item",
   "class": "weapon_nailgun",
   "kind": "ng",
   "name": "ng-4",
   "x": 152,
   "y": -974,
   "z": -52
  },
  {
   "type": "spawn",
   "class": "info_player_deathmatch",
   "name": "spawn-1",
   "x": -130,
   "y": 945,
   "z": -80
  },
  {
   "type": "spawn",
   "class": "info_player_deathmatch",
   "name": "spawn-2",
   "x": -128,
   "y": -944,
   "z": -72
  },
  {
   "type": "spawn",
   "class": "info_player_deathmatch",
   "name": "spawn-3",
   "x": -127,
   "y": 944,
   "z": 56
  },
  {
   "type": "spawn",
   "class": "info_player_deathmatch",
   "name": "spawn-4",
   "x": -124,
   "y": -944,
   "z": 56
  },
  {
   "type": "spawn",
   "class": "info_player_deathmatch",
   "name": "spawn-5",
   "x": 122,
   "y": -943,
   "z": 58
  },
  {
   "type": "spawn",
   "class": "info_player_deathmatch",
   "name": "spawn-6",
   "x": 124,
   "y": -943,
   "z": -72
  },
  {
   "type": "spawn",
   "class": "info_player_deathmatch",
   "name": "spawn-7",
   "x": 124,
   "y": 944,
   "z": -72
  }
 ]
}
