{
 "map": "genocide",
 "version": 1,
 "entities": [
  {
   "type": "item",
   "class": "item_cells",
   "kind": "cells",
   "name": "cells-1",
   "x": -1376,
   "y": -368,
   "z": -304
  },
  {
   "type": "item",
   "class": "item_cells",
   "kind": "cells",
   "name": "cells-2",
   "x": -1376,
   "y": -320,
   "z": -304
  },
  {
   "type": "item",
   "class": "item_cells",
   "kind": "cells",
   "name": "cells-3",
   "x": -352,
   "y": 192,
   "z": -176
  },
  {
   "type": "item",
   "class": "item_cells",
   "kind": "cells",
   "name": "cells-4",
   "x": -304,
   "y": 192,
   "z": -176
  },
  {
   "type": "item",
   "class": "item_cells",
   "kind": "cells",
   "name": "cells-5",
   "x": -16,
   "y": 1136,
   "z": -368
  },
  {
   "type": "item",
   "class": "item_cells",
   "kind": "cells",
   "name": "cells-6",
   "x": 80,
   "y": 1136,
   "z": -368
  },
  {
   "type": "item",
   "class": "item_cells",
   "kind": "cells",
   "name": "cells-7",
   "x": 336,
   "y": -464,
   "z": -176
  },
  {
   "type": "item",
   "class": "weapon_grenadelauncher",
   "kind": "gl",
   "name": "gl",
   "x": -1440,
   "y": -432,
   "z": -112
  },
  {
   "type": "item",
   "class": "item_health",
   "kind": "h25",
   "name": "h25-1",
   "x": -784,
   "y": 528,
   "z": -192
  },
  {
   "type": "item",
   "class": "item_health",
   "kind": "h25",
   "name": "h25-2",
   "x": -752,
   "y": -192,
   "z": -128
  },
  {
   "type": "item",
   "class": "item_health",
   "kind": "h25",
   "name": "h25-3",
   "x": -752,
   "y": -144,
   "z": -128
  },
  {
   "type": "item",
   "class": "item_health",
   "kind": "h25",
   "name": "h25-4",
   "x": 240,
   "y": -304,
   "z": -192
  },
  {
   "type": "item",
   "class": "item_health",
   "kind": "h25",
   "name": "h25-5",
   "x": 240,
   "y": -240,
   "z": -192
  },
  {
   "type": "item",
   "class": "item_health",
   "kind": "h25",
   "name": "h25-6",
   "x": 240,
   "y": 560,
   "z": -384
  },
  {
   "type": "item",
   "class": "weapon_lightning",
   "kind": "lg",
   "name": "lg",
   "x": 48,
   "y": 1152,
   "z": -368
  },
  {
   "type": "item",
   "class": "item_health",
   "kind": "mh",
   "name": "mh",
   "x": -1360,
   "y": 176,
   "z": -240,
   "spawnflags": 2
  },
  {
   "type": "item",
   "class": "item_spikes",
   "kind": "nails",
   "name": "nails-1",
   "x": -1104,
   "y": -368,
   "z": -304
  },
  {
   "type": "item",
   "class": "item_spikes",
   "kind": "nails",
   "name": "nails-2",
   "x": -1056,
   "y": -368,
   "z": -304
  },
  {
   "type": "item",
   "class": "item_spikes",
   "kind": "nails",
   "name": "nails-3",
   "x": -544,
   "y": -304,
   "z": -304
  },
  {
   "type": "item",
   "class": "item_spikes",
   "kind": "nails",
   "name": "nails-4",
   "x": -496,
   "y": -304,
   "z": -304
  },
  {
   "type": "item",
   "class": "item_spikes",
   "kind": "nails",
   "name": "nails-5",
   "x": -336,
   "y": 736,
   "z": -176
  },
  {
   "type": "item",
   "class": "item_spikes",
   "kind": "nails",
   "name": "nails-6",
   "x": -336,
   "y": 928,
   "z": -176
  },
  {
   "type": "item",
   "class": "item_artifact_super_damage",
   "kind": "quad",
   "name": "quad",
   "x": 256,
   "y": 832,
   "z": 0
  },
  {
   "type": "item",
   "class": "item_armorInv",
   "kind": "ra",
   "name": "ra",
   "x": 96,
   "y": 864,
   "z": -352
  },
  {
   "type": "item",
   "class": "item_artifact_invisibility",
   "kind": "ring",
   "name": "ring",
   "x": 448,
   "y": -656,
   "z": -160
  },
  {
   "type": "item",
   "class": "weapon_rocketlauncher",
   "kind": "rl",
   "name": "rl-1",
   "x": 64,
   "y": -96,
   "z": -176
  },
  {
   "type": "item",
   "class": "weapon_rocketlauncher",
   "kind": "rl",
   "name": "rl-2",
   "x": 96,
   "y": 1152,
   "z": -160
  },
  {
   "type": "item",
   "class": "item_rockets",
   "kind": "rockets",
   "name": "rockets-1",
   "x": -872,
   "y": 536,
   "z": -160
  },
  {
   "type": "item",
   "class": "item_rockets",
   "kind": "rockets",
   "name": "rockets-2",
   "x": -824,
   "y": 536,
   "z": -160
  },
  {
   "type": "item",
   "class": "item_rockets",
   "kind": "rockets",
   "name": "rockets-3",
   "x": -328,
   "y": 840,
   "z": -176
  },
  {
   "type": "item",
   "class": "item_rockets",
   "kind": "rockets",
   "name": "rockets-4",
   "x": -72,
   "y": 504,
   "z": -368
  },
  {
   "type": "item",
   "class": "item_rockets",
   "kind": "rockets",
   "name": "rockets-5",
   "x": -24,
   "y": 504,
   "z": -368
  },
  {
   "type": "item",
   "class": "item_rockets",
   "kind": "rockets",
   "name": "rockets-6",
   "x": 248,
   "y": 24,
   "z": -176
  },
  {
   "type": "item",
   "class": "item_rockets",
   "kind": "rockets",
   "name": "rockets-7",
   "x": 248,
   "y": 72,
   "z": -176
  },
  {
   "type": "item",
   "class": "item_rockets",
   "kind": "rockets",
   "name": "rockets-8",
   "x": 440,
   "y": -456,
   "z": -176
  },
  {
   "type": "item",
   "class": "item_shells",
   "kind": "shells",
   "name": "shells-1",
   "x": -736,
   "y": 528,
   "z": -160
  },
  {
   "type": "item",
   "class": "item_shells",
   "kind": "shells",
   "name": "shells-2",
   "x": -16,
   "y": -880,
   "z": -176
  },
  {
   "type": "item",
   "class": "item_shells",
   "kind": "shells",
   "name": "shells-3",
   "x": -16,
   "y": -848,
   "z": -176
  },
  {
   "type": "item",
   "class": "item_shells",
   "kind": "shells",
   "name": "shells-4",
   "x": 384,
   "y": -464,
   "z": -176
  },
  {
   "type": "item",
   "class": "weapon_supernailgun",
   "kind": "sng",
   "name": "sng",
   "x": -1008,
   "y": 128,
   "z": -304
  },
  {
   "type": "item",
   "class": "weapon_supershotgun",
   "kind": "ssg",
   "name": "ssg",
   "x": 240,
   "y": -656,
   "z": -240
  },
  {
   "type": "item",
   "class": "item_armor2",
   "kind": "ya",
   "name": "ya",
   "x": -368,
   "y": -384,
   "z": -112
  },
  {
   "type": "spawn",
   "class": "info_player_deathmatch",
   "name": "spawn-1",
   "x": -1488,
   "y": -560,
   "z": -96
  },
  {
   "type": "spawn",
   "class": "info_player_deathmatch",
   "name": "spawn-2",
   "x": -1456,
   "y": 384,
   "z": -224
  },
  {
   "type": "spawn",
   "class": "info_player_deathmatch",
   "name": "spawn-3",
   "x": -768,
   "y": 0,
   "z": -288
  },
  {
   "type": "spawn",
   "class": "info_player_deathmatch",
   "name": "spawn-4",
   "x": -592,
   "y": 32,
   "z": -288
  },
  {
   "type": "spawn",
   "class": "info_player_deathmatch",
   "name": "spawn-5",
   "x": -352,
   "y": 848,
   "z": -352
  },
  {
   "type": "spawn",
   "class": "info_player_deathmatch",
   "name": "spawn-6",
   "x": -160,
   "y": -592,
   "z": -224
  },
  {
   "type": "spawn",
   "class": "info_player_deathmatch",
   "name": "spawn-7",
   "x": 96,
   "y": 320,
   "z": -160
  },
  {
   "type": "spawn",
   "class": "info_player_deathmatch",
   "name": "spawn-8",
   "x": 240,
   "y": -832,
   "z": -160
  }
 ]
}
