{
 "map": "virtual",
 "version": 1,
 "entities": [
  {
   "type": "item",
   "class": "item_cells",
   "kind": "cells",
   "name": "cells-1",
   "x": -112,
   "y": 272,
   "z": 128,
   "spawnflags": 1
  },
  {
   "type": "item",
   "class": "item_cells",
   "kind": "cells",
   "name": "cells-2",
   "x": -80,
   "y": 136,
   "z": 128,
   "spawnflags": 1
  },
  {
   "type": "item",
   "class": "weapon_grenadelauncher",
   "kind": "gl",
   "name": "gl",
   "x": -576,
   "y": 719,
   "z": 173
  },
  {
   "type": "item",
   "class": "item_health",
   "kind": "h25",
   "name": "h25-1",
   "x": -773,
   "y": 938,
   "z": 187
  },
  {
   "type": "item",
   "class": "item_health",
   "kind": "h25",
   "name": "h25-2",
   "x": -520,
   "y": 247,
   "z": 175
  },
  {
   "type": "item",
   "class": "item_health",
   "kind": "h25",
   "name": "h25-3",
   "x": -516,
   "y": -211,
   "z": 180
  },
  {
   "type": "item",
   "class": "item_health",
   "kind": "h25",
   "name": "h25-4",
   "x": -497,
   "y": 502,
   "z": 171
  },
  {
   "type": "item",
   "class": "item_health",
   "kind": "h25",
   "name": "h25-5",
   "x": 587,
   "y": -47,
   "z": 243
  },
  {
   "type": "item",
   "class": "item_health",
   "kind": "h25",
   "name": "h25-6",
   "x": 740,
   "y": 241,
   "z": 69
  },
  {
   "type": "item",
   "class": "weapon_lightning",
   "kind": "lg",
   "name": "lg-1",
   "x": -2355,
   "y": 347,
   "z": 208
  },
  {
   "type": "item",
   "class": "weapon_lightning",
   "kind": "lg",
   "name": "lg-2",
   "x": -946,
   "y": 858,
   "z": 111
  },
  {
   "type": "item",
   "class": "item_health",
   "kind": "mh",
   "name": "mh",
   "x": 254,
   "y": 358,
   "z": 180,
   "spawnflags": 2
  },
  {
   "type": "item",
   "class": "item_spikes",
   "kind": "nails",
   "name": "nails-1",
   "x": -2347,
   "y": 843,
   "z": 208
  },
  {
   "type": "item",
   "class": "item_spikes",
   "kind": "nails",
   "name": "nails-2",
   "x": -1787,
   "y": 235,
   "z": 208
  },
  {
   "type": "item",
   "class": "item_spikes",
   "kind": "nails",
   "name": "nails-3",
   "x": -1771,
   "y": 1111,
   "z": 208
  },
  {
   "type": "item",
   "class": "item_spikes",
   "kind": "nails",
   "name": "nails-4",
   "x": -1715,
   "y": 235,
   "z": 208
  },
  {
   "type": "item",
   "class": "weapon_nailgun",
   "kind": "ng",
   "name": "ng-1",
   "x": -2063,
   "y": 1135,
   "z": 208
  },
  {
   "type": "item",
   "class": "weapon_nailgun",
   "kind": "ng",
   "name": "ng-2",
   "x": 736,
   "y": -44,
   "z": 233
  },
  {
   "type": "item",
   "class": "item_artifact_invulnerability",
   "kind": "pent",
   "name": "pent",
   "x": -1229,
   "y": 1138,
   "z": 201
  },
  {
   "type": "item",
   "class": "item_artifact_super_damage",
   "kind": "quad",
   "name": "quad-1",
   "x": -388,
   "y": 961,
   "z": 446
  },
  {
   "type": "item",
   "class": "item_artifact_super_damage",
   "kind": "quad",
   "name": "quad-2",
   "x": 256,
   "y": 216,
   "z": 185
  },
  {
   "type": "item",
   "class": "item_armorInv",
   "kind": "ra",
   "name": "ra",
   "x": -1229,
   "y": 844,
   "z": 187
  },
  {
   "type": "item",
   "class": "weapon_rocketlauncher",
   "kind": "rl",
   "name": "rl-1",
   "x": -940,
   "y": 512,
   "z": 144
  },
  {
   "type": "item",
   "class": "weapon_rocketlauncher",
   "kind": "rl",
   "name": "rl-2",
   "x": 200,
   "y": -360,
   "z": 80
  },
  {
   "type": "item",
   "class": "item_rockets",
   "kind": "rockets",
   "name": "rockets-1",
   "x": -1360,
   "y": 1136,
   "z": 160,
   "spawnflags": 1
  },
  {
   "type": "item",
   "class": "item_rockets",
   "kind": "rockets",
   "name": "rockets-2",
   "x": -1120,
   "y": 1136,
   "z": 160,
   "spawnflags": 1
  },
  {
   "type": "item",
   "class": "item_shells",
   "kind": "shells",
   "name": "shells-1",
   "x": -2359,
   "y": 507,
   "z": 208
  },
  {
   "type": "item",
   "class": "item_shells",
   "kind": "shells",
   "name": "shells-2",
   "x": -2211,
   "y": 1127,
   "z": 208
  },
  {
   "type": "item",
   "class": "item_shells",
   "kind": "shells",
   "name": "shells-3",
   "x": -2183,
   "y": 251,
   "z": 208
  },
  {
   "type": "item",
   "class": "item_shells",
   "kind": "shells",
   "name": "shells-4",
   "x": -1551,
   "y": 911,
   "z": 208
  },
  {
   "type": "item",
   "class": "weapon_supernailgun",
   "kind": "sng",
   "name": "sng-1",
   "x": -391,
   "y": 437,
   "z": 410
  },
  {
   "type": "item",
   "class": "weapon_supernailgun",
   "kind": "sng",
   "name": "sng-2",
   "x": -336,
   "y": 50,
   "z": 128
  },
  {
   "type": "item",
   "class": "weapon_supernailgun",
   "kind": "sng",
   "name": "sng-3",
   "x": 263,
   "y": 236,
   "z": 78
  },
  {
   "type": "item",
   "class": "weapon_supershotgun",
   "kind": "ssg",
   "name": "ssg",
   "x": 604,
   "y": -413,
   "z": 60
  },
  {
   "type": "item",
   "class": "item_artifact_envirosuit",
   "kind": "suit",
   "name": "suit",
   "x": 72,
   "y": -120,
   "z": 120
  },
  {
   "type": "spawn",
   "class": "info_player_deathmatch",
   "name": "spawn-1",
   "x": -2382,
   "y": 301,
   "z": 168
  },
  {
   "type": "spawn",
   "class": "info_player_deathmatch",
   "name": "spawn-10",
   "x": 752,
   "y": 227,
   "z": 56
  },
  {
   "type": "spawn",
   "class": "info_player_deathmatch",
   "name": "spawn-2",
   "x": -1552,
   "y": 1097,
   "z": 168
  },
  {
   "type": "spawn",
   "class": "info_player_deathmatch",
   "name": "spawn-3",
   "x": -1312,
   "y": 719,
   "z": 184
  },
  {
   "type": "spawn",
   "class": "info_player_deathmatch",
   "name": "spawn-4",
   "x": -942,
   "y": -366,
   "z": 152
  },
  {
   "type": "spawn",
   "class": "info_player_deathmatch",
   "name": "spawn-5",
   "x": -592,
   "y": 719,
   "z": 168
  },
  {
   "type": "spawn",
   "class": "info_player_deathmatch",
   "name": "spawn-6",
   "x": -96,
   "y": -11,
   "z": 168
  },
  {
   "type": "spawn",
   "class": "info_player_start",
   "name": "spawn-7",
   "x": 88,
   "y": 224,
   "z": 56
  },
  {
   "type": "spawn",
   "class": "info_player_deathmatch",
   "name": "spawn-8",
   "x": 144,
   "y": 224,
   "z": 56
  },
  {
   "type": "spawn",
   "class": "info_player_deathmatch",
   "name": "spawn-9",
   "x": 300,
   "y": -347,
   "z": 168
  },
  {
   "type": "teleportDst",
   "class": "info_teleport_destination",
   "name": "tele-dst-1",
   "x": -2274,
   "y": 246,
   "z": 168,
   "targetName": "t4"
  },
  {
   "type": "teleportDst",
   "class": "info_teleport_destination",
   "name": "tele-dst-2",
   "x": -392,
   "y": 624,
   "z": 408,
   "targetName": "t2"
  },
  {
   "type": "teleportDst",
   "class": "info_teleport_destination",
   "name": "tele-dst-3",
   "x": 120,
   "y": 337,
   "z": 56,
   "targetName": "t3"
  }
 ]
}
